MANIFEST.in
ez_setup.py
setup.py
GauminIpuinWriter.egg-info/PKG-INFO
GauminIpuinWriter.egg-info/SOURCES.txt
GauminIpuinWriter.egg-info/dependency_links.txt
GauminIpuinWriter.egg-info/entry_points.txt
GauminIpuinWriter.egg-info/not-zip-safe
GauminIpuinWriter.egg-info/requires.txt
GauminIpuinWriter.egg-info/top_level.txt
gauminipuinwriter/__init__.py
gauminipuinwriter/__main__.py
gauminipuinwriter/main.py
gauminipuinwriter/writer.kv
gauminipuinwriter/imgs/empty.png
gauminipuinwriter/imgs/gaumin_logo.png